{
  "version": "tree-0.1",
  "tree": {
    "id": "App",
    "path": "",
    "children": {
      "Tree": {
        "id": "Tree",
        "path": "Tree",
        "constructInfo": {
          "fqn": "constructs.Construct",
          "version": "10.1.74"
        }
      },
      "FargateStack": {
        "id": "FargateStack",
        "path": "FargateStack",
        "children": {
          "FargateNextjs": {
            "id": "FargateNextjs",
            "path": "FargateStack/FargateNextjs",
            "children": {
              "Resource": {
                "id": "Resource",
                "path": "FargateStack/FargateNextjs/Resource",
                "attributes": {
                  "aws:cdk:cloudformation:type": "AWS::EC2::VPC",
                  "aws:cdk:cloudformation:props": {
                    "cidrBlock": "10.0.0.0/16",
                    "enableDnsHostnames": true,
                    "enableDnsSupport": true,
                    "instanceTenancy": "default",
                    "tags": [
                      {
                        "key": "Name",
                        "value": "FargateStack/FargateNextjs"
                      }
                    ]
                  }
                },
                "constructInfo": {
                  "fqn": "aws-cdk-lib.aws_ec2.CfnVPC",
                  "version": "2.37.1"
                }
              },
              "PublicSubnet1": {
                "id": "PublicSubnet1",
                "path": "FargateStack/FargateNextjs/PublicSubnet1",
                "children": {
                  "Subnet": {
                    "id": "Subnet",
                    "path": "FargateStack/FargateNextjs/PublicSubnet1/Subnet",
                    "attributes": {
                      "aws:cdk:cloudformation:type": "AWS::EC2::Subnet",
                      "aws:cdk:cloudformation:props": {
                        "vpcId": {
                          "Ref": "FargateNextjs1E9565CA"
                        },
                        "availabilityZone": {
                          "Fn::Select": [
                            0,
                            {
                              "Fn::GetAZs": ""
                            }
                          ]
                        },
                        "cidrBlock": "10.0.0.0/18",
                        "mapPublicIpOnLaunch": true,
                        "tags": [
                          {
                            "key": "aws-cdk:subnet-name",
                            "value": "Public"
                          },
                          {
                            "key": "aws-cdk:subnet-type",
                            "value": "Public"
                          },
                          {
                            "key": "Name",
                            "value": "FargateStack/FargateNextjs/PublicSubnet1"
                          }
                        ]
                      }
                    },
                    "constructInfo": {
                      "fqn": "aws-cdk-lib.aws_ec2.CfnSubnet",
                      "version": "2.37.1"
                    }
                  },
                  "Acl": {
                    "id": "Acl",
                    "path": "FargateStack/FargateNextjs/PublicSubnet1/Acl",
                    "constructInfo": {
                      "fqn": "aws-cdk-lib.Resource",
                      "version": "2.37.1"
                    }
                  },
                  "RouteTable": {
                    "id": "RouteTable",
                    "path": "FargateStack/FargateNextjs/PublicSubnet1/RouteTable",
                    "attributes": {
                      "aws:cdk:cloudformation:type": "AWS::EC2::RouteTable",
                      "aws:cdk:cloudformation:props": {
                        "vpcId": {
                          "Ref": "FargateNextjs1E9565CA"
                        },
                        "tags": [
                          {
                            "key": "Name",
                            "value": "FargateStack/FargateNextjs/PublicSubnet1"
                          }
                        ]
                      }
                    },
                    "constructInfo": {
                      "fqn": "aws-cdk-lib.aws_ec2.CfnRouteTable",
                      "version": "2.37.1"
                    }
                  },
                  "RouteTableAssociation": {
                    "id": "RouteTableAssociation",
                    "path": "FargateStack/FargateNextjs/PublicSubnet1/RouteTableAssociation",
                    "attributes": {
                      "aws:cdk:cloudformation:type": "AWS::EC2::SubnetRouteTableAssociation",
                      "aws:cdk:cloudformation:props": {
                        "routeTableId": {
                          "Ref": "FargateNextjsPublicSubnet1RouteTable6A7EDFB2"
                        },
                        "subnetId": {
                          "Ref": "FargateNextjsPublicSubnet1SubnetF36CF5D5"
                        }
                      }
                    },
                    "constructInfo": {
                      "fqn": "aws-cdk-lib.aws_ec2.CfnSubnetRouteTableAssociation",
                      "version": "2.37.1"
                    }
                  },
                  "DefaultRoute": {
                    "id": "DefaultRoute",
                    "path": "FargateStack/FargateNextjs/PublicSubnet1/DefaultRoute",
                    "attributes": {
                      "aws:cdk:cloudformation:type": "AWS::EC2::Route",
                      "aws:cdk:cloudformation:props": {
                        "routeTableId": {
                          "Ref": "FargateNextjsPublicSubnet1RouteTable6A7EDFB2"
                        },
                        "destinationCidrBlock": "0.0.0.0/0",
                        "gatewayId": {
                          "Ref": "FargateNextjsIGW49CE7223"
                        }
                      }
                    },
                    "constructInfo": {
                      "fqn": "aws-cdk-lib.aws_ec2.CfnRoute",
                      "version": "2.37.1"
                    }
                  },
                  "EIP": {
                    "id": "EIP",
                    "path": "FargateStack/FargateNextjs/PublicSubnet1/EIP",
                    "attributes": {
                      "aws:cdk:cloudformation:type": "AWS::EC2::EIP",
                      "aws:cdk:cloudformation:props": {
                        "domain": "vpc",
                        "tags": [
                          {
                            "key": "Name",
                            "value": "FargateStack/FargateNextjs/PublicSubnet1"
                          }
                        ]
                      }
                    },
                    "constructInfo": {
                      "fqn": "aws-cdk-lib.aws_ec2.CfnEIP",
                      "version": "2.37.1"
                    }
                  },
                  "NATGateway": {
                    "id": "NATGateway",
                    "path": "FargateStack/FargateNextjs/PublicSubnet1/NATGateway",
                    "attributes": {
                      "aws:cdk:cloudformation:type": "AWS::EC2::NatGateway",
                      "aws:cdk:cloudformation:props": {
                        "subnetId": {
                          "Ref": "FargateNextjsPublicSubnet1SubnetF36CF5D5"
                        },
                        "allocationId": {
                          "Fn::GetAtt": [
                            "FargateNextjsPublicSubnet1EIP1E2E27E7",
                            "AllocationId"
                          ]
                        },
                        "tags": [
                          {
                            "key": "Name",
                            "value": "FargateStack/FargateNextjs/PublicSubnet1"
                          }
                        ]
                      }
                    },
                    "constructInfo": {
                      "fqn": "aws-cdk-lib.aws_ec2.CfnNatGateway",
                      "version": "2.37.1"
                    }
                  }
                },
                "constructInfo": {
                  "fqn": "aws-cdk-lib.aws_ec2.PublicSubnet",
                  "version": "2.37.1"
                }
              },
              "PublicSubnet2": {
                "id": "PublicSubnet2",
                "path": "FargateStack/FargateNextjs/PublicSubnet2",
                "children": {
                  "Subnet": {
                    "id": "Subnet",
                    "path": "FargateStack/FargateNextjs/PublicSubnet2/Subnet",
                    "attributes": {
                      "aws:cdk:cloudformation:type": "AWS::EC2::Subnet",
                      "aws:cdk:cloudformation:props": {
                        "vpcId": {
                          "Ref": "FargateNextjs1E9565CA"
                        },
                        "availabilityZone": {
                          "Fn::Select": [
                            1,
                            {
                              "Fn::GetAZs": ""
                            }
                          ]
                        },
                        "cidrBlock": "10.0.64.0/18",
                        "mapPublicIpOnLaunch": true,
                        "tags": [
                          {
                            "key": "aws-cdk:subnet-name",
                            "value": "Public"
                          },
                          {
                            "key": "aws-cdk:subnet-type",
                            "value": "Public"
                          },
                          {
                            "key": "Name",
                            "value": "FargateStack/FargateNextjs/PublicSubnet2"
                          }
                        ]
                      }
                    },
                    "constructInfo": {
                      "fqn": "aws-cdk-lib.aws_ec2.CfnSubnet",
                      "version": "2.37.1"
                    }
                  },
                  "Acl": {
                    "id": "Acl",
                    "path": "FargateStack/FargateNextjs/PublicSubnet2/Acl",
                    "constructInfo": {
                      "fqn": "aws-cdk-lib.Resource",
                      "version": "2.37.1"
                    }
                  },
                  "RouteTable": {
                    "id": "RouteTable",
                    "path": "FargateStack/FargateNextjs/PublicSubnet2/RouteTable",
                    "attributes": {
                      "aws:cdk:cloudformation:type": "AWS::EC2::RouteTable",
                      "aws:cdk:cloudformation:props": {
                        "vpcId": {
                          "Ref": "FargateNextjs1E9565CA"
                        },
                        "tags": [
                          {
                            "key": "Name",
                            "value": "FargateStack/FargateNextjs/PublicSubnet2"
                          }
                        ]
                      }
                    },
                    "constructInfo": {
                      "fqn": "aws-cdk-lib.aws_ec2.CfnRouteTable",
                      "version": "2.37.1"
                    }
                  },
                  "RouteTableAssociation": {
                    "id": "RouteTableAssociation",
                    "path": "FargateStack/FargateNextjs/PublicSubnet2/RouteTableAssociation",
                    "attributes": {
                      "aws:cdk:cloudformation:type": "AWS::EC2::SubnetRouteTableAssociation",
                      "aws:cdk:cloudformation:props": {
                        "routeTableId": {
                          "Ref": "FargateNextjsPublicSubnet2RouteTable9853ED88"
                        },
                        "subnetId": {
                          "Ref": "FargateNextjsPublicSubnet2SubnetFDB1D52A"
                        }
                      }
                    },
                    "constructInfo": {
                      "fqn": "aws-cdk-lib.aws_ec2.CfnSubnetRouteTableAssociation",
                      "version": "2.37.1"
                    }
                  },
                  "DefaultRoute": {
                    "id": "DefaultRoute",
                    "path": "FargateStack/FargateNextjs/PublicSubnet2/DefaultRoute",
                    "attributes": {
                      "aws:cdk:cloudformation:type": "AWS::EC2::Route",
                      "aws:cdk:cloudformation:props": {
                        "routeTableId": {
                          "Ref": "FargateNextjsPublicSubnet2RouteTable9853ED88"
                        },
                        "destinationCidrBlock": "0.0.0.0/0",
                        "gatewayId": {
                          "Ref": "FargateNextjsIGW49CE7223"
                        }
                      }
                    },
                    "constructInfo": {
                      "fqn": "aws-cdk-lib.aws_ec2.CfnRoute",
                      "version": "2.37.1"
                    }
                  },
                  "EIP": {
                    "id": "EIP",
                    "path": "FargateStack/FargateNextjs/PublicSubnet2/EIP",
                    "attributes": {
                      "aws:cdk:cloudformation:type": "AWS::EC2::EIP",
                      "aws:cdk:cloudformation:props": {
                        "domain": "vpc",
                        "tags": [
                          {
                            "key": "Name",
                            "value": "FargateStack/FargateNextjs/PublicSubnet2"
                          }
                        ]
                      }
                    },
                    "constructInfo": {
                      "fqn": "aws-cdk-lib.aws_ec2.CfnEIP",
                      "version": "2.37.1"
                    }
                  },
                  "NATGateway": {
                    "id": "NATGateway",
                    "path": "FargateStack/FargateNextjs/PublicSubnet2/NATGateway",
                    "attributes": {
                      "aws:cdk:cloudformation:type": "AWS::EC2::NatGateway",
                      "aws:cdk:cloudformation:props": {
                        "subnetId": {
                          "Ref": "FargateNextjsPublicSubnet2SubnetFDB1D52A"
                        },
                        "allocationId": {
                          "Fn::GetAtt": [
                            "FargateNextjsPublicSubnet2EIP9CB215A7",
                            "AllocationId"
                          ]
                        },
                        "tags": [
                          {
                            "key": "Name",
                            "value": "FargateStack/FargateNextjs/PublicSubnet2"
                          }
                        ]
                      }
                    },
                    "constructInfo": {
                      "fqn": "aws-cdk-lib.aws_ec2.CfnNatGateway",
                      "version": "2.37.1"
                    }
                  }
                },
                "constructInfo": {
                  "fqn": "aws-cdk-lib.aws_ec2.PublicSubnet",
                  "version": "2.37.1"
                }
              },
              "PrivateSubnet1": {
                "id": "PrivateSubnet1",
                "path": "FargateStack/FargateNextjs/PrivateSubnet1",
                "children": {
                  "Subnet": {
                    "id": "Subnet",
                    "path": "FargateStack/FargateNextjs/PrivateSubnet1/Subnet",
                    "attributes": {
                      "aws:cdk:cloudformation:type": "AWS::EC2::Subnet",
                      "aws:cdk:cloudformation:props": {
                        "vpcId": {
                          "Ref": "FargateNextjs1E9565CA"
                        },
                        "availabilityZone": {
                          "Fn::Select": [
                            0,
                            {
                              "Fn::GetAZs": ""
                            }
                          ]
                        },
                        "cidrBlock": "10.0.128.0/18",
                        "mapPublicIpOnLaunch": false,
                        "tags": [
                          {
                            "key": "aws-cdk:subnet-name",
                            "value": "Private"
                          },
                          {
                            "key": "aws-cdk:subnet-type",
                            "value": "Private"
                          },
                          {
                            "key": "Name",
                            "value": "FargateStack/FargateNextjs/PrivateSubnet1"
                          }
                        ]
                      }
                    },
                    "constructInfo": {
                      "fqn": "aws-cdk-lib.aws_ec2.CfnSubnet",
                      "version": "2.37.1"
                    }
                  },
                  "Acl": {
                    "id": "Acl",
                    "path": "FargateStack/FargateNextjs/PrivateSubnet1/Acl",
                    "constructInfo": {
                      "fqn": "aws-cdk-lib.Resource",
                      "version": "2.37.1"
                    }
                  },
                  "RouteTable": {
                    "id": "RouteTable",
                    "path": "FargateStack/FargateNextjs/PrivateSubnet1/RouteTable",
                    "attributes": {
                      "aws:cdk:cloudformation:type": "AWS::EC2::RouteTable",
                      "aws:cdk:cloudformation:props": {
                        "vpcId": {
                          "Ref": "FargateNextjs1E9565CA"
                        },
                        "tags": [
                          {
                            "key": "Name",
                            "value": "FargateStack/FargateNextjs/PrivateSubnet1"
                          }
                        ]
                      }
                    },
                    "constructInfo": {
                      "fqn": "aws-cdk-lib.aws_ec2.CfnRouteTable",
                      "version": "2.37.1"
                    }
                  },
                  "RouteTableAssociation": {
                    "id": "RouteTableAssociation",
                    "path": "FargateStack/FargateNextjs/PrivateSubnet1/RouteTableAssociation",
                    "attributes": {
                      "aws:cdk:cloudformation:type": "AWS::EC2::SubnetRouteTableAssociation",
                      "aws:cdk:cloudformation:props": {
                        "routeTableId": {
                          "Ref": "FargateNextjsPrivateSubnet1RouteTable5D1CB703"
                        },
                        "subnetId": {
                          "Ref": "FargateNextjsPrivateSubnet1SubnetBDB8E0C5"
                        }
                      }
                    },
                    "constructInfo": {
                      "fqn": "aws-cdk-lib.aws_ec2.CfnSubnetRouteTableAssociation",
                      "version": "2.37.1"
                    }
                  },
                  "DefaultRoute": {
                    "id": "DefaultRoute",
                    "path": "FargateStack/FargateNextjs/PrivateSubnet1/DefaultRoute",
                    "attributes": {
                      "aws:cdk:cloudformation:type": "AWS::EC2::Route",
                      "aws:cdk:cloudformation:props": {
                        "routeTableId": {
                          "Ref": "FargateNextjsPrivateSubnet1RouteTable5D1CB703"
                        },
                        "destinationCidrBlock": "0.0.0.0/0",
                        "natGatewayId": {
                          "Ref": "FargateNextjsPublicSubnet1NATGateway4D1FF63A"
                        }
                      }
                    },
                    "constructInfo": {
                      "fqn": "aws-cdk-lib.aws_ec2.CfnRoute",
                      "version": "2.37.1"
                    }
                  }
                },
                "constructInfo": {
                  "fqn": "aws-cdk-lib.aws_ec2.PrivateSubnet",
                  "version": "2.37.1"
                }
              },
              "PrivateSubnet2": {
                "id": "PrivateSubnet2",
                "path": "FargateStack/FargateNextjs/PrivateSubnet2",
                "children": {
                  "Subnet": {
                    "id": "Subnet",
                    "path": "FargateStack/FargateNextjs/PrivateSubnet2/Subnet",
                    "attributes": {
                      "aws:cdk:cloudformation:type": "AWS::EC2::Subnet",
                      "aws:cdk:cloudformation:props": {
                        "vpcId": {
                          "Ref": "FargateNextjs1E9565CA"
                        },
                        "availabilityZone": {
                          "Fn::Select": [
                            1,
                            {
                              "Fn::GetAZs": ""
                            }
                          ]
                        },
                        "cidrBlock": "10.0.192.0/18",
                        "mapPublicIpOnLaunch": false,
                        "tags": [
                          {
                            "key": "aws-cdk:subnet-name",
                            "value": "Private"
                          },
                          {
                            "key": "aws-cdk:subnet-type",
                            "value": "Private"
                          },
                          {
                            "key": "Name",
                            "value": "FargateStack/FargateNextjs/PrivateSubnet2"
                          }
                        ]
                      }
                    },
                    "constructInfo": {
                      "fqn": "aws-cdk-lib.aws_ec2.CfnSubnet",
                      "version": "2.37.1"
                    }
                  },
                  "Acl": {
                    "id": "Acl",
                    "path": "FargateStack/FargateNextjs/PrivateSubnet2/Acl",
                    "constructInfo": {
                      "fqn": "aws-cdk-lib.Resource",
                      "version": "2.37.1"
                    }
                  },
                  "RouteTable": {
                    "id": "RouteTable",
                    "path": "FargateStack/FargateNextjs/PrivateSubnet2/RouteTable",
                    "attributes": {
                      "aws:cdk:cloudformation:type": "AWS::EC2::RouteTable",
                      "aws:cdk:cloudformation:props": {
                        "vpcId": {
                          "Ref": "FargateNextjs1E9565CA"
                        },
                        "tags": [
                          {
                            "key": "Name",
                            "value": "FargateStack/FargateNextjs/PrivateSubnet2"
                          }
                        ]
                      }
                    },
                    "constructInfo": {
                      "fqn": "aws-cdk-lib.aws_ec2.CfnRouteTable",
                      "version": "2.37.1"
                    }
                  },
                  "RouteTableAssociation": {
                    "id": "RouteTableAssociation",
                    "path": "FargateStack/FargateNextjs/PrivateSubnet2/RouteTableAssociation",
                    "attributes": {
                      "aws:cdk:cloudformation:type": "AWS::EC2::SubnetRouteTableAssociation",
                      "aws:cdk:cloudformation:props": {
                        "routeTableId": {
                          "Ref": "FargateNextjsPrivateSubnet2RouteTable0DFD84E1"
                        },
                        "subnetId": {
                          "Ref": "FargateNextjsPrivateSubnet2Subnet7F06468F"
                        }
                      }
                    },
                    "constructInfo": {
                      "fqn": "aws-cdk-lib.aws_ec2.CfnSubnetRouteTableAssociation",
                      "version": "2.37.1"
                    }
                  },
                  "DefaultRoute": {
                    "id": "DefaultRoute",
                    "path": "FargateStack/FargateNextjs/PrivateSubnet2/DefaultRoute",
                    "attributes": {
                      "aws:cdk:cloudformation:type": "AWS::EC2::Route",
                      "aws:cdk:cloudformation:props": {
                        "routeTableId": {
                          "Ref": "FargateNextjsPrivateSubnet2RouteTable0DFD84E1"
                        },
                        "destinationCidrBlock": "0.0.0.0/0",
                        "natGatewayId": {
                          "Ref": "FargateNextjsPublicSubnet2NATGateway46906B73"
                        }
                      }
                    },
                    "constructInfo": {
                      "fqn": "aws-cdk-lib.aws_ec2.CfnRoute",
                      "version": "2.37.1"
                    }
                  }
                },
                "constructInfo": {
                  "fqn": "aws-cdk-lib.aws_ec2.PrivateSubnet",
                  "version": "2.37.1"
                }
              },
              "IGW": {
                "id": "IGW",
                "path": "FargateStack/FargateNextjs/IGW",
                "attributes": {
                  "aws:cdk:cloudformation:type": "AWS::EC2::InternetGateway",
                  "aws:cdk:cloudformation:props": {
                    "tags": [
                      {
                        "key": "Name",
                        "value": "FargateStack/FargateNextjs"
                      }
                    ]
                  }
                },
                "constructInfo": {
                  "fqn": "aws-cdk-lib.aws_ec2.CfnInternetGateway",
                  "version": "2.37.1"
                }
              },
              "VPCGW": {
                "id": "VPCGW",
                "path": "FargateStack/FargateNextjs/VPCGW",
                "attributes": {
                  "aws:cdk:cloudformation:type": "AWS::EC2::VPCGatewayAttachment",
                  "aws:cdk:cloudformation:props": {
                    "vpcId": {
                      "Ref": "FargateNextjs1E9565CA"
                    },
                    "internetGatewayId": {
                      "Ref": "FargateNextjsIGW49CE7223"
                    }
                  }
                },
                "constructInfo": {
                  "fqn": "aws-cdk-lib.aws_ec2.CfnVPCGatewayAttachment",
                  "version": "2.37.1"
                }
              }
            },
            "constructInfo": {
              "fqn": "aws-cdk-lib.aws_ec2.Vpc",
              "version": "2.37.1"
            }
          },
          "ClusterNextjs": {
            "id": "ClusterNextjs",
            "path": "FargateStack/ClusterNextjs",
            "children": {
              "Resource": {
                "id": "Resource",
                "path": "FargateStack/ClusterNextjs/Resource",
                "attributes": {
                  "aws:cdk:cloudformation:type": "AWS::ECS::Cluster",
                  "aws:cdk:cloudformation:props": {}
                },
                "constructInfo": {
                  "fqn": "aws-cdk-lib.aws_ecs.CfnCluster",
                  "version": "2.37.1"
                }
              }
            },
            "constructInfo": {
              "fqn": "aws-cdk-lib.aws_ecs.Cluster",
              "version": "2.37.1"
            }
          },
          "BuildImageNextjs": {
            "id": "BuildImageNextjs",
            "path": "FargateStack/BuildImageNextjs",
            "children": {
              "Staging": {
                "id": "Staging",
                "path": "FargateStack/BuildImageNextjs/Staging",
                "constructInfo": {
                  "fqn": "aws-cdk-lib.AssetStaging",
                  "version": "2.37.1"
                }
              },
              "Repository": {
                "id": "Repository",
                "path": "FargateStack/BuildImageNextjs/Repository",
                "constructInfo": {
                  "fqn": "aws-cdk-lib.aws_ecr.RepositoryBase",
                  "version": "2.37.1"
                }
              }
            },
            "constructInfo": {
              "fqn": "aws-cdk-lib.aws_ecr_assets.DockerImageAsset",
              "version": "2.37.1"
            }
          },
          "RepoNextjs": {
            "id": "RepoNextjs",
            "path": "FargateStack/RepoNextjs",
            "children": {
              "Resource": {
                "id": "Resource",
                "path": "FargateStack/RepoNextjs/Resource",
                "attributes": {
                  "aws:cdk:cloudformation:type": "AWS::ECR::Repository",
                  "aws:cdk:cloudformation:props": {
                    "imageScanningConfiguration": {
                      "scanOnPush": true
                    }
                  }
                },
                "constructInfo": {
                  "fqn": "aws-cdk-lib.aws_ecr.CfnRepository",
                  "version": "2.37.1"
                }
              }
            },
            "constructInfo": {
              "fqn": "aws-cdk-lib.aws_ecr.Repository",
              "version": "2.37.1"
            }
          },
          "FargateService": {
            "id": "FargateService",
            "path": "FargateStack/FargateService",
            "children": {
              "LB": {
                "id": "LB",
                "path": "FargateStack/FargateService/LB",
                "children": {
                  "Resource": {
                    "id": "Resource",
                    "path": "FargateStack/FargateService/LB/Resource",
                    "attributes": {
                      "aws:cdk:cloudformation:type": "AWS::ElasticLoadBalancingV2::LoadBalancer",
                      "aws:cdk:cloudformation:props": {
                        "loadBalancerAttributes": [
                          {
                            "key": "deletion_protection.enabled",
                            "value": "false"
                          }
                        ],
                        "scheme": "internet-facing",
                        "securityGroups": [
                          {
                            "Fn::GetAtt": [
                              "FargateServiceLBSecurityGroup5F444C78",
                              "GroupId"
                            ]
                          }
                        ],
                        "subnets": [
                          {
                            "Ref": "FargateNextjsPublicSubnet1SubnetF36CF5D5"
                          },
                          {
                            "Ref": "FargateNextjsPublicSubnet2SubnetFDB1D52A"
                          }
                        ],
                        "type": "application"
                      }
                    },
                    "constructInfo": {
                      "fqn": "aws-cdk-lib.aws_elasticloadbalancingv2.CfnLoadBalancer",
                      "version": "2.37.1"
                    }
                  },
                  "SecurityGroup": {
                    "id": "SecurityGroup",
                    "path": "FargateStack/FargateService/LB/SecurityGroup",
                    "children": {
                      "Resource": {
                        "id": "Resource",
                        "path": "FargateStack/FargateService/LB/SecurityGroup/Resource",
                        "attributes": {
                          "aws:cdk:cloudformation:type": "AWS::EC2::SecurityGroup",
                          "aws:cdk:cloudformation:props": {
                            "groupDescription": "Automatically created Security Group for ELB FargateStackFargateServiceLB9049C732",
                            "securityGroupIngress": [
                              {
                                "cidrIp": "0.0.0.0/0",
                                "ipProtocol": "tcp",
                                "fromPort": 80,
                                "toPort": 80,
                                "description": "Allow from anyone on port 80"
                              }
                            ],
                            "vpcId": {
                              "Ref": "FargateNextjs1E9565CA"
                            }
                          }
                        },
                        "constructInfo": {
                          "fqn": "aws-cdk-lib.aws_ec2.CfnSecurityGroup",
                          "version": "2.37.1"
                        }
                      },
                      "to FargateStackFargateServiceSecurityGroupB04BEC81:80": {
                        "id": "to FargateStackFargateServiceSecurityGroupB04BEC81:80",
                        "path": "FargateStack/FargateService/LB/SecurityGroup/to FargateStackFargateServiceSecurityGroupB04BEC81:80",
                        "attributes": {
                          "aws:cdk:cloudformation:type": "AWS::EC2::SecurityGroupEgress",
                          "aws:cdk:cloudformation:props": {
                            "groupId": {
                              "Fn::GetAtt": [
                                "FargateServiceLBSecurityGroup5F444C78",
                                "GroupId"
                              ]
                            },
                            "ipProtocol": "tcp",
                            "description": "Load balancer to target",
                            "destinationSecurityGroupId": {
                              "Fn::GetAtt": [
                                "FargateServiceSecurityGroup262B61DD",
                                "GroupId"
                              ]
                            },
                            "fromPort": 80,
                            "toPort": 80
                          }
                        },
                        "constructInfo": {
                          "fqn": "aws-cdk-lib.aws_ec2.CfnSecurityGroupEgress",
                          "version": "2.37.1"
                        }
                      }
                    },
                    "constructInfo": {
                      "fqn": "aws-cdk-lib.aws_ec2.SecurityGroup",
                      "version": "2.37.1"
                    }
                  },
                  "PublicListener": {
                    "id": "PublicListener",
                    "path": "FargateStack/FargateService/LB/PublicListener",
                    "children": {
                      "Resource": {
                        "id": "Resource",
                        "path": "FargateStack/FargateService/LB/PublicListener/Resource",
                        "attributes": {
                          "aws:cdk:cloudformation:type": "AWS::ElasticLoadBalancingV2::Listener",
                          "aws:cdk:cloudformation:props": {
                            "defaultActions": [
                              {
                                "type": "forward",
                                "targetGroupArn": {
                                  "Ref": "FargateServiceLBPublicListenerECSGroupBE57E081"
                                }
                              }
                            ],
                            "loadBalancerArn": {
                              "Ref": "FargateServiceLBB353E155"
                            },
                            "port": 80,
                            "protocol": "HTTP"
                          }
                        },
                        "constructInfo": {
                          "fqn": "aws-cdk-lib.aws_elasticloadbalancingv2.CfnListener",
                          "version": "2.37.1"
                        }
                      },
                      "ECSGroup": {
                        "id": "ECSGroup",
                        "path": "FargateStack/FargateService/LB/PublicListener/ECSGroup",
                        "children": {
                          "Resource": {
                            "id": "Resource",
                            "path": "FargateStack/FargateService/LB/PublicListener/ECSGroup/Resource",
                            "attributes": {
                              "aws:cdk:cloudformation:type": "AWS::ElasticLoadBalancingV2::TargetGroup",
                              "aws:cdk:cloudformation:props": {
                                "port": 80,
                                "protocol": "HTTP",
                                "targetGroupAttributes": [
                                  {
                                    "key": "stickiness.enabled",
                                    "value": "false"
                                  }
                                ],
                                "targetType": "ip",
                                "vpcId": {
                                  "Ref": "FargateNextjs1E9565CA"
                                }
                              }
                            },
                            "constructInfo": {
                              "fqn": "aws-cdk-lib.aws_elasticloadbalancingv2.CfnTargetGroup",
                              "version": "2.37.1"
                            }
                          }
                        },
                        "constructInfo": {
                          "fqn": "aws-cdk-lib.aws_elasticloadbalancingv2.ApplicationTargetGroup",
                          "version": "2.37.1"
                        }
                      }
                    },
                    "constructInfo": {
                      "fqn": "aws-cdk-lib.aws_elasticloadbalancingv2.ApplicationListener",
                      "version": "2.37.1"
                    }
                  }
                },
                "constructInfo": {
                  "fqn": "aws-cdk-lib.aws_elasticloadbalancingv2.ApplicationLoadBalancer",
                  "version": "2.37.1"
                }
              },
              "LoadBalancerDNS": {
                "id": "LoadBalancerDNS",
                "path": "FargateStack/FargateService/LoadBalancerDNS",
                "constructInfo": {
                  "fqn": "aws-cdk-lib.CfnOutput",
                  "version": "2.37.1"
                }
              },
              "ServiceURL": {
                "id": "ServiceURL",
                "path": "FargateStack/FargateService/ServiceURL",
                "constructInfo": {
                  "fqn": "aws-cdk-lib.CfnOutput",
                  "version": "2.37.1"
                }
              },
              "TaskDef": {
                "id": "TaskDef",
                "path": "FargateStack/FargateService/TaskDef",
                "children": {
                  "TaskRole": {
                    "id": "TaskRole",
                    "path": "FargateStack/FargateService/TaskDef/TaskRole",
                    "children": {
                      "Resource": {
                        "id": "Resource",
                        "path": "FargateStack/FargateService/TaskDef/TaskRole/Resource",
                        "attributes": {
                          "aws:cdk:cloudformation:type": "AWS::IAM::Role",
                          "aws:cdk:cloudformation:props": {
                            "assumeRolePolicyDocument": {
                              "Statement": [
                                {
                                  "Action": "sts:AssumeRole",
                                  "Effect": "Allow",
                                  "Principal": {
                                    "Service": "ecs-tasks.amazonaws.com"
                                  }
                                }
                              ],
                              "Version": "2012-10-17"
                            }
                          }
                        },
                        "constructInfo": {
                          "fqn": "aws-cdk-lib.aws_iam.CfnRole",
                          "version": "2.37.1"
                        }
                      }
                    },
                    "constructInfo": {
                      "fqn": "aws-cdk-lib.aws_iam.Role",
                      "version": "2.37.1"
                    }
                  },
                  "Resource": {
                    "id": "Resource",
                    "path": "FargateStack/FargateService/TaskDef/Resource",
                    "attributes": {
                      "aws:cdk:cloudformation:type": "AWS::ECS::TaskDefinition",
                      "aws:cdk:cloudformation:props": {
                        "containerDefinitions": [
                          {
                            "cpu": 512,
                            "essential": true,
                            "image": {
                              "Fn::Join": [
                                "",
                                [
                                  {
                                    "Fn::Select": [
                                      4,
                                      {
                                        "Fn::Split": [
                                          ":",
                                          {
                                            "Fn::GetAtt": [
                                              "RepoNextjsBF548028",
                                              "Arn"
                                            ]
                                          }
                                        ]
                                      }
                                    ]
                                  },
                                  ".dkr.ecr.",
                                  {
                                    "Fn::Select": [
                                      3,
                                      {
                                        "Fn::Split": [
                                          ":",
                                          {
                                            "Fn::GetAtt": [
                                              "RepoNextjsBF548028",
                                              "Arn"
                                            ]
                                          }
                                        ]
                                      }
                                    ]
                                  },
                                  ".",
                                  {
                                    "Ref": "AWS::URLSuffix"
                                  },
                                  "/",
                                  {
                                    "Ref": "RepoNextjsBF548028"
                                  },
                                  ":latest"
                                ]
                              ]
                            },
                            "memory": 1024,
                            "name": "web",
                            "portMappings": [
                              {
                                "containerPort": 80,
                                "protocol": "tcp"
                              }
                            ],
                            "logConfiguration": {
                              "logDriver": "awslogs",
                              "options": {
                                "awslogs-group": {
                                  "Ref": "FargateServiceTaskDefwebLogGroup71FAF541"
                                },
                                "awslogs-stream-prefix": "FargateService",
                                "awslogs-region": {
                                  "Ref": "AWS::Region"
                                }
                              }
                            }
                          }
                        ],
                        "cpu": "512",
                        "executionRoleArn": {
                          "Fn::GetAtt": [
                            "FargateServiceTaskDefExecutionRole9194820E",
                            "Arn"
                          ]
                        },
                        "family": "FargateStackFargateServiceTaskDefABBD8B00",
                        "memory": "1024",
                        "networkMode": "awsvpc",
                        "requiresCompatibilities": [
                          "FARGATE"
                        ],
                        "taskRoleArn": {
                          "Fn::GetAtt": [
                            "FargateServiceTaskDefTaskRole8CDCF85E",
                            "Arn"
                          ]
                        }
                      }
                    },
                    "constructInfo": {
                      "fqn": "aws-cdk-lib.aws_ecs.CfnTaskDefinition",
                      "version": "2.37.1"
                    }
                  },
                  "web": {
                    "id": "web",
                    "path": "FargateStack/FargateService/TaskDef/web",
                    "children": {
                      "LogGroup": {
                        "id": "LogGroup",
                        "path": "FargateStack/FargateService/TaskDef/web/LogGroup",
                        "children": {
                          "Resource": {
                            "id": "Resource",
                            "path": "FargateStack/FargateService/TaskDef/web/LogGroup/Resource",
                            "attributes": {
                              "aws:cdk:cloudformation:type": "AWS::Logs::LogGroup",
                              "aws:cdk:cloudformation:props": {}
                            },
                            "constructInfo": {
                              "fqn": "aws-cdk-lib.aws_logs.CfnLogGroup",
                              "version": "2.37.1"
                            }
                          }
                        },
                        "constructInfo": {
                          "fqn": "aws-cdk-lib.aws_logs.LogGroup",
                          "version": "2.37.1"
                        }
                      }
                    },
                    "constructInfo": {
                      "fqn": "aws-cdk-lib.aws_ecs.ContainerDefinition",
                      "version": "2.37.1"
                    }
                  },
                  "ExecutionRole": {
                    "id": "ExecutionRole",
                    "path": "FargateStack/FargateService/TaskDef/ExecutionRole",
                    "children": {
                      "Resource": {
                        "id": "Resource",
                        "path": "FargateStack/FargateService/TaskDef/ExecutionRole/Resource",
                        "attributes": {
                          "aws:cdk:cloudformation:type": "AWS::IAM::Role",
                          "aws:cdk:cloudformation:props": {
                            "assumeRolePolicyDocument": {
                              "Statement": [
                                {
                                  "Action": "sts:AssumeRole",
                                  "Effect": "Allow",
                                  "Principal": {
                                    "Service": "ecs-tasks.amazonaws.com"
                                  }
                                }
                              ],
                              "Version": "2012-10-17"
                            }
                          }
                        },
                        "constructInfo": {
                          "fqn": "aws-cdk-lib.aws_iam.CfnRole",
                          "version": "2.37.1"
                        }
                      },
                      "DefaultPolicy": {
                        "id": "DefaultPolicy",
                        "path": "FargateStack/FargateService/TaskDef/ExecutionRole/DefaultPolicy",
                        "children": {
                          "Resource": {
                            "id": "Resource",
                            "path": "FargateStack/FargateService/TaskDef/ExecutionRole/DefaultPolicy/Resource",
                            "attributes": {
                              "aws:cdk:cloudformation:type": "AWS::IAM::Policy",
                              "aws:cdk:cloudformation:props": {
                                "policyDocument": {
                                  "Statement": [
                                    {
                                      "Action": [
                                        "ecr:BatchCheckLayerAvailability",
                                        "ecr:GetDownloadUrlForLayer",
                                        "ecr:BatchGetImage"
                                      ],
                                      "Effect": "Allow",
                                      "Resource": {
                                        "Fn::GetAtt": [
                                          "RepoNextjsBF548028",
                                          "Arn"
                                        ]
                                      }
                                    },
                                    {
                                      "Action": "ecr:GetAuthorizationToken",
                                      "Effect": "Allow",
                                      "Resource": "*"
                                    },
                                    {
                                      "Action": [
                                        "logs:CreateLogStream",
                                        "logs:PutLogEvents"
                                      ],
                                      "Effect": "Allow",
                                      "Resource": {
                                        "Fn::GetAtt": [
                                          "FargateServiceTaskDefwebLogGroup71FAF541",
                                          "Arn"
                                        ]
                                      }
                                    }
                                  ],
                                  "Version": "2012-10-17"
                                },
                                "policyName": "FargateServiceTaskDefExecutionRoleDefaultPolicy827E7CA2",
                                "roles": [
                                  {
                                    "Ref": "FargateServiceTaskDefExecutionRole9194820E"
                                  }
                                ]
                              }
                            },
                            "constructInfo": {
                              "fqn": "aws-cdk-lib.aws_iam.CfnPolicy",
                              "version": "2.37.1"
                            }
                          }
                        },
                        "constructInfo": {
                          "fqn": "aws-cdk-lib.aws_iam.Policy",
                          "version": "2.37.1"
                        }
                      }
                    },
                    "constructInfo": {
                      "fqn": "aws-cdk-lib.aws_iam.Role",
                      "version": "2.37.1"
                    }
                  }
                },
                "constructInfo": {
                  "fqn": "aws-cdk-lib.aws_ecs.FargateTaskDefinition",
                  "version": "2.37.1"
                }
              },
              "Service": {
                "id": "Service",
                "path": "FargateStack/FargateService/Service",
                "children": {
                  "Service": {
                    "id": "Service",
                    "path": "FargateStack/FargateService/Service/Service",
                    "attributes": {
                      "aws:cdk:cloudformation:type": "AWS::ECS::Service",
                      "aws:cdk:cloudformation:props": {
                        "cluster": {
                          "Ref": "ClusterNextjs6E572403"
                        },
                        "deploymentConfiguration": {
                          "maximumPercent": 200,
                          "minimumHealthyPercent": 50
                        },
                        "desiredCount": 1,
                        "enableEcsManagedTags": false,
                        "healthCheckGracePeriodSeconds": 60,
                        "launchType": "FARGATE",
                        "loadBalancers": [
                          {
                            "targetGroupArn": {
                              "Ref": "FargateServiceLBPublicListenerECSGroupBE57E081"
                            },
                            "containerName": "web",
                            "containerPort": 80
                          }
                        ],
                        "networkConfiguration": {
                          "awsvpcConfiguration": {
                            "assignPublicIp": "DISABLED",
                            "subnets": [
                              {
                                "Ref": "FargateNextjsPrivateSubnet1SubnetBDB8E0C5"
                              },
                              {
                                "Ref": "FargateNextjsPrivateSubnet2Subnet7F06468F"
                              }
                            ],
                            "securityGroups": [
                              {
                                "Fn::GetAtt": [
                                  "FargateServiceSecurityGroup262B61DD",
                                  "GroupId"
                                ]
                              }
                            ]
                          }
                        },
                        "taskDefinition": {
                          "Ref": "FargateServiceTaskDef940E3A80"
                        }
                      }
                    },
                    "constructInfo": {
                      "fqn": "aws-cdk-lib.aws_ecs.CfnService",
                      "version": "2.37.1"
                    }
                  },
                  "SecurityGroup": {
                    "id": "SecurityGroup",
                    "path": "FargateStack/FargateService/Service/SecurityGroup",
                    "children": {
                      "Resource": {
                        "id": "Resource",
                        "path": "FargateStack/FargateService/Service/SecurityGroup/Resource",
                        "attributes": {
                          "aws:cdk:cloudformation:type": "AWS::EC2::SecurityGroup",
                          "aws:cdk:cloudformation:props": {
                            "groupDescription": "FargateStack/FargateService/Service/SecurityGroup",
                            "securityGroupEgress": [
                              {
                                "cidrIp": "0.0.0.0/0",
                                "description": "Allow all outbound traffic by default",
                                "ipProtocol": "-1"
                              }
                            ],
                            "vpcId": {
                              "Ref": "FargateNextjs1E9565CA"
                            }
                          }
                        },
                        "constructInfo": {
                          "fqn": "aws-cdk-lib.aws_ec2.CfnSecurityGroup",
                          "version": "2.37.1"
                        }
                      },
                      "from FargateStackFargateServiceLBSecurityGroup0598A7EA:80": {
                        "id": "from FargateStackFargateServiceLBSecurityGroup0598A7EA:80",
                        "path": "FargateStack/FargateService/Service/SecurityGroup/from FargateStackFargateServiceLBSecurityGroup0598A7EA:80",
                        "attributes": {
                          "aws:cdk:cloudformation:type": "AWS::EC2::SecurityGroupIngress",
                          "aws:cdk:cloudformation:props": {
                            "ipProtocol": "tcp",
                            "description": "Load balancer to target",
                            "fromPort": 80,
                            "groupId": {
                              "Fn::GetAtt": [
                                "FargateServiceSecurityGroup262B61DD",
                                "GroupId"
                              ]
                            },
                            "sourceSecurityGroupId": {
                              "Fn::GetAtt": [
                                "FargateServiceLBSecurityGroup5F444C78",
                                "GroupId"
                              ]
                            },
                            "toPort": 80
                          }
                        },
                        "constructInfo": {
                          "fqn": "aws-cdk-lib.aws_ec2.CfnSecurityGroupIngress",
                          "version": "2.37.1"
                        }
                      }
                    },
                    "constructInfo": {
                      "fqn": "aws-cdk-lib.aws_ec2.SecurityGroup",
                      "version": "2.37.1"
                    }
                  }
                },
                "constructInfo": {
                  "fqn": "aws-cdk-lib.aws_ecs.FargateService",
                  "version": "2.37.1"
                }
              }
            },
            "constructInfo": {
              "fqn": "aws-cdk-lib.aws_ecs_patterns.ApplicationLoadBalancedFargateService",
              "version": "2.37.1"
            }
          },
          "CDKMetadata": {
            "id": "CDKMetadata",
            "path": "FargateStack/CDKMetadata",
            "children": {
              "Default": {
                "id": "Default",
                "path": "FargateStack/CDKMetadata/Default",
                "constructInfo": {
                  "fqn": "aws-cdk-lib.CfnResource",
                  "version": "2.37.1"
                }
              },
              "Condition": {
                "id": "Condition",
                "path": "FargateStack/CDKMetadata/Condition",
                "constructInfo": {
                  "fqn": "aws-cdk-lib.CfnCondition",
                  "version": "2.37.1"
                }
              }
            },
            "constructInfo": {
              "fqn": "constructs.Construct",
              "version": "10.1.74"
            }
          }
        },
        "constructInfo": {
          "fqn": "aws-cdk-lib.Stack",
          "version": "2.37.1"
        }
      }
    },
    "constructInfo": {
      "fqn": "aws-cdk-lib.App",
      "version": "2.37.1"
    }
  }
}